sepinn/__init__.py
sepinn/hublayer.py
sepinn/pinn.py
sepinn/wrappedpinn.py
sepinn-1.0.0.dist-info/METADATA
sepinn-1.0.0.dist-info/WHEEL
sepinn-1.0.0.dist-info/licenses/LICENSE
sepinn-1.0.0.dist-info/RECORD
