Metadata-Version: 2.3
Name: sepinn
Version: 1.0.0
Summary: Solving the Schrödinger Equation via Physics-Informed Machine Learning
Project-URL: Homepage, https://tiger-du.github.io/sepinn.html
Project-URL: Repository, https://github.com/Tiger-Du/SE-PINN
Requires-Dist: matplotlib>=3.7.1
Requires-Dist: numpy>=1.23.5
Requires-Dist: scipy>=1.11.4
Requires-Dist: torch>=2.1.0
